MilightWifiBridge/MilightWifiBridge.py
MilightWifiBridge/__init__.py
MilightWifiBridge-2.1.1.dist-info/LICENSE.txt
MilightWifiBridge-2.1.1.dist-info/METADATA
MilightWifiBridge-2.1.1.dist-info/WHEEL
MilightWifiBridge-2.1.1.dist-info/top_level.txt
MilightWifiBridge-2.1.1.dist-info/RECORD
