Metadata-Version: 2.1
Name: MilightWifiBridge
Version: 2.1.1
Summary: Milight Wifi Bridge 3.0 controller for LimitlessLED Wifi Bridge v6.0 protocol (Light ON/OFF, change color/mode/brightness/saturation, link/unlink)
Home-page: https://github.com/QuentinCG/Milight-Wifi-Bridge-3.0-Python-Library
Author: Quentin Comte-Gaz
Author-email: quentin@comte-gaz.com
License: MIT
Keywords: milight bulbs home automation limitlessled ibox link unlink light night white color saturation brightness disco mode speed mac
Platform: any
Classifier: Development Status :: 5 - Production/Stable
Classifier: Topic :: Home Automation
Classifier: Topic :: Software Development :: Libraries
Classifier: Topic :: Software Development :: Libraries :: Python Modules
Classifier: Intended Audience :: Developers
Classifier: License :: OSI Approved :: MIT License
Classifier: Operating System :: Microsoft :: Windows
Classifier: Operating System :: POSIX :: Linux
Classifier: Operating System :: MacOS
Classifier: Natural Language :: English
Classifier: Programming Language :: Python :: 2.7
Classifier: Programming Language :: Python :: 3
Classifier: Programming Language :: Python :: 3.2
Classifier: Programming Language :: Python :: 3.3
Classifier: Programming Language :: Python :: 3.4
Classifier: Programming Language :: Python :: 3.5
Classifier: Programming Language :: Python :: 3.6
Classifier: Programming Language :: Python :: 3.7
Classifier: Programming Language :: Python :: 3.8
Classifier: Programming Language :: Python :: 3.9
License-File: LICENSE.txt
